hcpre/__init__.py
hcpre/config.py
hcpre/hcpipe.py
hcpre/interfaces.py
hcpre/util.py
hcpre/workflows.py
hcpre/duke_siemens/__init__.py
hcpre/duke_siemens/__init__.pyc
hcpre/duke_siemens/constants.py
hcpre/duke_siemens/constants.pyc
hcpre/duke_siemens/LICENSE
hcpre/duke_siemens/Readme.txt
hcpre/duke_siemens/util_dicom_siemens.py
hcpre/duke_siemens/util_dicom_siemens.pyc
hcpre/duke_siemens/util_mrs_file.py
hcpre/duke_siemens/util_mrs_file.pyc
hcpre-0.5.5.data/scripts/hcpipe.py
hcpre-0.5.5.dist-info/DESCRIPTION.rst
hcpre-0.5.5.dist-info/METADATA
hcpre-0.5.5.dist-info/metadata.json
hcpre-0.5.5.dist-info/RECORD
hcpre-0.5.5.dist-info/top_level.txt
hcpre-0.5.5.dist-info/WHEEL
