Metadata-Version: 2.0
Name: hcpre
Version: 0.5.5
Summary: Generalized launcher for human connectome project BOLD preprocessing
Home-page: https://github.com/beOn/hcpre
Author: Ben Acland
Author-email: benacland@gmail.com
License: BSD
Keywords: connectome preprocessing fmri bold
Platform: UNKNOWN
Classifier: Development Status :: 3 - Alpha
Classifier: Topic :: Scientific/Engineering :: Information Analysis
Classifier: License :: OSI Approved :: BSD License
Classifier: Intended Audience :: Science/Research
Requires-Dist: pydicom
Requires-Dist: nibabel
Requires-Dist: networkx
Requires-Dist: traits
Requires-Dist: nipype
Requires-Dist: configobj
